{ "frames": [
   {
    "filename": "Bright_Light 0.aseprite",
    "frame": { "x": 0, "y": 0, "w": 64, "h": 64 },
    "rotated": false,
    "trimmed": false,
    "spriteSourceSize": { "x": 0, "y": 0, "w": 64, "h": 64 },
    "sourceSize": { "w": 64, "h": 64 },
    "duration": 100
   },
   {
    "filename": "Bright_Light 1.aseprite",
    "frame": { "x": 69, "y": 0, "w": 64, "h": 64 },
    "rotated": false,
    "trimmed": false,
    "spriteSourceSize": { "x": 0, "y": 0, "w": 64, "h": 64 },
    "sourceSize": { "w": 64, "h": 64 },
    "duration": 100
   },
   {
    "filename": "Bright_Light 2.aseprite",
    "frame": { "x": 138, "y": 0, "w": 64, "h": 64 },
    "rotated": false,
    "trimmed": false,
    "spriteSourceSize": { "x": 0, "y": 0, "w": 64, "h": 64 },
    "sourceSize": { "w": 64, "h": 64 },
    "duration": 100
   },
   {
    "filename": "Bright_Light 3.aseprite",
    "frame": { "x": 207, "y": 0, "w": 64, "h": 64 },
    "rotated": false,
    "trimmed": false,
    "spriteSourceSize": { "x": 0, "y": 0, "w": 64, "h": 64 },
    "sourceSize": { "w": 64, "h": 64 },
    "duration": 100
   },
   {
    "filename": "Bright_Light 4.aseprite",
    "frame": { "x": 276, "y": 0, "w": 64, "h": 64 },
    "rotated": false,
    "trimmed": false,
    "spriteSourceSize": { "x": 0, "y": 0, "w": 64, "h": 64 },
    "sourceSize": { "w": 64, "h": 64 },
    "duration": 100
   },
   {
    "filename": "Bright_Light 5.aseprite",
    "frame": { "x": 345, "y": 0, "w": 64, "h": 64 },
    "rotated": false,
    "trimmed": false,
    "spriteSourceSize": { "x": 0, "y": 0, "w": 64, "h": 64 },
    "sourceSize": { "w": 64, "h": 64 },
    "duration": 100
   },
   {
    "filename": "Bright_Light 6.aseprite",
    "frame": { "x": 414, "y": 0, "w": 64, "h": 64 },
    "rotated": false,
    "trimmed": false,
    "spriteSourceSize": { "x": 0, "y": 0, "w": 64, "h": 64 },
    "sourceSize": { "w": 64, "h": 64 },
    "duration": 100
   },
   {
    "filename": "Bright_Light 7.aseprite",
    "frame": { "x": 483, "y": 0, "w": 64, "h": 64 },
    "rotated": false,
    "trimmed": false,
    "spriteSourceSize": { "x": 0, "y": 0, "w": 64, "h": 64 },
    "sourceSize": { "w": 64, "h": 64 },
    "duration": 100
   }
 ],
 "meta": {
  "app": "http://www.aseprite.org/",
  "version": "1.2.25-x64",
  "image": "Bright_Light.png",
  "format": "RGBA8888",
  "size": { "w": 547, "h": 64 },
  "scale": "1",
  "frameTags": [
  ],
  "layers": [
   { "name": "Layer 1", "opacity": 255, "blendMode": "normal" }
  ],
  "slices": [
  ]
 }
}
